easy_gtfs/__init__.py
easy_gtfs/agency.txt
easy_gtfs/managers/__init__.py
easy_gtfs/managers/agencymanager.py
easy_gtfs/managers/errormanager.py
easy_gtfs/managers/gtfsmanager.py
easy_gtfs/managers/stopmanager.py
easy_gtfs/models/__init__.py
easy_gtfs/models/errors.py
easy_gtfs/models/models.py
easy_gtfs/objects/__init__.py
easy_gtfs/objects/agency.py
easy_gtfs/objects/stop.py
easy_gtfs/sample-feed.zip
easy_gtfs/utility.py
easy_gtfs/variables.py
easy_gtfs-0.1.0.4.dist-info/METADATA
easy_gtfs-0.1.0.4.dist-info/WHEEL
easy_gtfs-0.1.0.4.dist-info/RECORD
