Metadata-Version: 2.1
Name: easy-gtfs
Version: 0.1.0.4
Summary: This package allows loading and saving folders containing GTFS data.
Author: Felix3qH4
Author-email: 89027442+Felix3qH4@users.noreply.github.com
Requires-Python: >=3.9,<4.0
Classifier: Programming Language :: Python :: 3
Classifier: Programming Language :: Python :: 3.9
Classifier: Programming Language :: Python :: 3.10
Classifier: Programming Language :: Python :: 3.11
